ubigeos_peru/__init__.py
ubigeos_peru/core/__init__.py
ubigeos_peru/core/__init__.pyi
ubigeos_peru/core/_utils.py
ubigeos_peru/core/resource_manager.py
ubigeos_peru/core/ubigeo_converter.py
ubigeos_peru/core/validations.py
ubigeos_peru/resources/__init__.py
ubigeos_peru/resources/departamentos.json
ubigeos_peru/resources/distritos.json
ubigeos_peru/resources/equivalencias.json
ubigeos_peru/resources/global.json
ubigeos_peru/resources/inverted.json
ubigeos_peru/resources/macrorregiones.json
ubigeos_peru/resources/otros.json
ubigeos_peru/resources/provincias.json
ubigeos_peru-0.2.2.dist-info/licenses/LICENSE
ubigeos_peru-0.2.2.dist-info/METADATA
ubigeos_peru-0.2.2.dist-info/WHEEL
ubigeos_peru-0.2.2.dist-info/top_level.txt
ubigeos_peru-0.2.2.dist-info/RECORD
