Metadata-Version: 2.4
Name: ubigeos-peru
Version: 0.2.2
Summary: Librería de Python que convierte códigos de ubigeo en su correspondiente departamento, provincia o distrito, y viceversa, además de información suplementaria.
Author-email: Michael Suárez <michael-salvador@hotmail.com>
License-Expression: MIT
Project-URL: Homepage, https://github.com/MichaelSuarez0/ubigeos_peru
Keywords: ubigeo,peru,departamentos,provincias,distritos,enaho
Requires-Python: <3.13,>=3.9
License-File: LICENSE
Requires-Dist: orjson
Requires-Dist: rapidfuzz
Dynamic: license-file
